{
    "QoE": 97.397558,
    "timestamp": 20250402122754,
    "20250402122746": {
        "throughput": 1536.6,
        "packets_lost": 0.0,
        "packet_loss_rate": 0.0,
        "jitter": 15.066,
        "speed": 0
    },
    "20250402122748": {
        "throughput": 605.2,
        "packets_lost": 0.0,
        "packet_loss_rate": 0.0,
        "jitter": 20.468,
        "speed": 0
    },
    "20250402122750": {
        "throughput": 974.0,
        "packets_lost": 1.0,
        "packet_loss_rate": 0.5,
        "jitter": 22.172,
        "speed": 0
    },
    "20250402122752": {
        "throughput": 1257.6,
        "packets_lost": 3.0,
        "packet_loss_rate": 1.1,
        "jitter": 17.835,
        "speed": 0
    },
    "20250402122754": {
        "throughput": 1413.7,
        "packets_lost": 0.0,
        "packet_loss_rate": 0.0,
        "jitter": 15.74,
        "speed": 0
    }
}